odetoolbox/__init__.py
odetoolbox/analytic_integrator.py
odetoolbox/config.py
odetoolbox/dependency_graph_plotter.py
odetoolbox/integrator.py
odetoolbox/mixed_integrator.py
odetoolbox/plot_helper.py
odetoolbox/shapes.py
odetoolbox/singularity_detection.py
odetoolbox/spike_generator.py
odetoolbox/stiffness.py
odetoolbox/sympy_helpers.py
odetoolbox/system_of_shapes.py
odetoolbox-2.5.10.data/scripts/ode_analyzer.py
odetoolbox-2.5.10.dist-info/LICENSE.md
odetoolbox-2.5.10.dist-info/METADATA
odetoolbox-2.5.10.dist-info/WHEEL
odetoolbox-2.5.10.dist-info/top_level.txt
odetoolbox-2.5.10.dist-info/RECORD
