Metadata-Version: 2.1
Name: odetoolbox
Version: 2.5.10
Summary: ODE-toolbox: Automatic selection and generation of integration schemes for systems of ordinary differential equations
Home-page: https://github.com/nest/ode-toolbox
Author: The NEST Initiative
License: GNU General Public License v2 (GPLv2)
Keywords: computational neuroscience model ordinary differential equation ode dynamical dynamic simulation
Classifier: Development Status :: 4 - Beta
Classifier: Environment :: Console
Classifier: Intended Audience :: Science/Research
Classifier: License :: OSI Approved :: GNU General Public License v2 (GPLv2)
Classifier: Natural Language :: English
Classifier: Operating System :: OS Independent
Classifier: Programming Language :: Python :: 3
Classifier: Topic :: Scientific/Engineering
Requires: matplotlib
Requires: numpy
Requires: sympy
License-File: LICENSE.md
